LICENSE
MANIFEST.in
README.rst
pytest_memprof.py
setup.py
pytest_memprof.egg-info/PKG-INFO
pytest_memprof.egg-info/SOURCES.txt
pytest_memprof.egg-info/dependency_links.txt
pytest_memprof.egg-info/entry_points.txt
pytest_memprof.egg-info/not-zip-safe
pytest_memprof.egg-info/requires.txt
pytest_memprof.egg-info/top_level.txt